gocept.template_rewrite-1.1-py3.9-nspkg.pth
gocept/template_rewrite/__init__.py
gocept/template_rewrite/dtml.py
gocept/template_rewrite/lib2to3.py
gocept/template_rewrite/main.py
gocept/template_rewrite/pagetemplates.py
gocept/template_rewrite/tests/__init__.py
gocept/template_rewrite/tests/test_dtml.py
gocept/template_rewrite/tests/test_lib2to3.py
gocept/template_rewrite/tests/test_main.py
gocept/template_rewrite/tests/test_pagetemplates.py
gocept/template_rewrite/tests/fixture/broken/broken.pt
gocept/template_rewrite/tests/fixture/broken/broken2.pt
gocept/template_rewrite/tests/fixture/broken/broken3.pt
gocept/template_rewrite/tests/fixture/sane/README.txt
gocept/template_rewrite/tests/fixture/sane/broken.html
gocept/template_rewrite/tests/fixture/sane/one.pt
gocept/template_rewrite/tests/fixture/sane/three.xpt
gocept/template_rewrite/tests/fixture/sane/two.dtml
gocept.template_rewrite-1.1.data/data/CHANGES.rst
gocept.template_rewrite-1.1.data/data/HACKING.rst
gocept.template_rewrite-1.1.data/data/LICENSE.txt
gocept.template_rewrite-1.1.data/data/README.rst
gocept.template_rewrite-1.1.dist-info/LICENSE.txt
gocept.template_rewrite-1.1.dist-info/METADATA
gocept.template_rewrite-1.1.dist-info/WHEEL
gocept.template_rewrite-1.1.dist-info/entry_points.txt
gocept.template_rewrite-1.1.dist-info/namespace_packages.txt
gocept.template_rewrite-1.1.dist-info/top_level.txt
gocept.template_rewrite-1.1.dist-info/RECORD
