Metadata-Version: 2.1
Name: gocept.template-rewrite
Version: 1.1
Summary: A tool to rewrite parts of template files (DTML, ZPT).
Home-page: https://github.com/gocept/gocept.template_rewrite/
Author: gocept <mail@gocept.com>
Author-email: mail@gocept.com
License: MIT
Keywords: Zope DTML ZPT pagetemplates migrate Python 3
Platform: UNKNOWN
Classifier: Development Status :: 4 - Beta
Classifier: Framework :: Zope
Classifier: Intended Audience :: Developers
Classifier: License :: OSI Approved
Classifier: License :: OSI Approved :: MIT License
Classifier: Operating System :: OS Independent
Classifier: Programming Language :: Python
Classifier: Programming Language :: Python :: 3
Classifier: Programming Language :: Python :: 3 :: Only
Classifier: Programming Language :: Python :: 3.6
Classifier: Programming Language :: Python :: 3.7
Classifier: Programming Language :: Python :: 3.8
Classifier: Programming Language :: Python :: 3.9
Classifier: Programming Language :: Python :: 3.10
Classifier: Programming Language :: Python :: Implementation :: CPython
Classifier: Topic :: Text Processing :: Filters
Requires-Python: >=3.6, <4
License-File: LICENSE.txt
Requires-Dist: setuptools
Provides-Extra: test
Requires-Dist: pytest ; extra == 'test'
Requires-Dist: pytest-mock ; extra == 'test'
